magicify/__init__.py
magicify/magic.py
magicify-1.2.3.dist-info/WHEEL
magicify-1.2.3.dist-info/METADATA
magicify-1.2.3.dist-info/RECORD
