Metadata-Version: 2.1
Name: magicify
Version: 1.2.3
Summary: Make everything magical
Author-email: Ben Brady <benbrady04.bb@gmail.com>
Requires-Python: >=3.9
